nonebot_plugin_morep_finder/__init__.py
nonebot_plugin_morep_finder/app.py
nonebot_plugin_morep_finder/config.py
nonebot_plugin_morep_finder/lib.py
nonebot_plugin_morep_finder-1.0.0.dist-info/LICENSE
nonebot_plugin_morep_finder-1.0.0.dist-info/METADATA
nonebot_plugin_morep_finder-1.0.0.dist-info/WHEEL
nonebot_plugin_morep_finder-1.0.0.dist-info/top_level.txt
nonebot_plugin_morep_finder-1.0.0.dist-info/RECORD
