Metadata-Version: 2.1
Name: nonebot-plugin-morep-finder
Version: 1.0.0
Summary: Nonebot2 plugin. (only for kaheila adaptor)
Author-email: Kl1nge5 <ninthseason@qq.com>
License: GPL-3.0-only
Keywords: nonebot2,kook,kaiheila
Classifier: Programming Language :: Python :: 3.8
Classifier: Programming Language :: Python :: 3.9
Classifier: Programming Language :: Python :: 3.10
Classifier: Programming Language :: Python :: 3.11
Classifier: License :: OSI Approved :: GNU General Public License v3 (GPLv3)
Requires-Python: >=3.8
License-File: LICENSE
Requires-Dist: nonebot2
Requires-Dist: nonebot-adapter-kaiheila
Requires-Dist: aiohttp
